aas_core3/__init__.py
aas_core3/common.py
aas_core3/constants.py
aas_core3/jsonization.py
aas_core3/py.typed
aas_core3/stringification.py
aas_core3/types.py
aas_core3/verification.py
aas_core3/xmlization.py
aas_core3_0-1.1.2.dist-info/licenses/AUTHORS
aas_core3_0-1.1.2.dist-info/licenses/LICENSE
dev_scripts/test_codegen/__init__.py
dev_scripts/test_codegen/common.py
dev_scripts/test_codegen/generate_all.py
dev_scripts/test_codegen/generate_common_jsonization.py
dev_scripts/test_codegen/generate_test_for_descend_and_pass_through_visitor.py
dev_scripts/test_codegen/generate_test_for_descend_once.py
dev_scripts/test_codegen/generate_test_for_jsonization_of_classes_with_descendants.py
dev_scripts/test_codegen/generate_test_for_jsonization_of_concrete_classes.py
dev_scripts/test_codegen/generate_test_for_jsonization_of_concrete_classes_outside_container.py
dev_scripts/test_codegen/generate_test_for_jsonization_of_enums.py
dev_scripts/test_codegen/generate_test_for_over_X_or_empty.py
dev_scripts/test_codegen/generate_test_for_x_or_default.py
dev_scripts/test_codegen/generate_test_for_xmlization_of_classes_with_descendants.py
dev_scripts/test_codegen/generate_test_for_xmlization_of_concrete_classes.py
dev_scripts/test_codegen/generate_test_for_xmlization_of_concrete_classes_outside_container.py
dev_scripts/test_codegen/test_data_io.py
aas_core3_0-1.1.2.dist-info/METADATA
aas_core3_0-1.1.2.dist-info/WHEEL
aas_core3_0-1.1.2.dist-info/top_level.txt
aas_core3_0-1.1.2.dist-info/RECORD
