Metadata-Version: 2.4
Name: aas-core3.0
Version: 1.1.2
Summary: Manipulate, verify and de/serialize Asset Administration Shells.
Home-page: https://github.com/aas-core-works/aas-core3.0-python
Author: Marko Ristin
Author-email: marko@ristin.ch
License: License :: OSI Approved :: MIT License
Keywords: asset administration shell sdk industry 4.0 industrie i4.0 industry iot iiot
Classifier: Development Status :: 5 - Production/Stable
Classifier: License :: OSI Approved :: MIT License
Classifier: Programming Language :: Python :: 3.8
Classifier: Programming Language :: Python :: 3.9
Classifier: Programming Language :: Python :: 3.10
Classifier: Programming Language :: Python :: 3.11
Classifier: Programming Language :: Python :: 3.12
License-File: LICENSE
License-File: AUTHORS
Dynamic: author
Dynamic: author-email
Dynamic: classifier
Dynamic: description
Dynamic: home-page
Dynamic: keywords
Dynamic: license
Dynamic: license-file
Dynamic: summary
